{
  "id": "DF0NWBDQXW28QATZQ890BZVDJB",
  "name": "Cinematic Night-Red",
  "slug": "cinematic-night-red-by-kazu-fujisawa",
  "category": "Nikon Creators",
  "tags": null,
  "description": null,
  "author": "Kazu Fujisawa",
  "authorLink": null,
  "whiteBalance": null,
  "whiteBalanceShift": null,
  "activeDLighting": null,
  "evComp": null,
  "grain": null,
  "note": null,
  "np3": "CINENigRed_Fuji.NP3",
  "images": [
    "CINENigRed_Fuji.jpg"
  ],
  "recipeLink": "https://imagingcloud.nikon.com/recipe/detail/?recipeId=01K5QFQYEAATKR29DPWPY5BC7Q"
}
