{
  "id": "VBVCH3AD9M28VHY10FWNQ0ERRZ",
  "name": "Purple Mood",
  "slug": "purple-mood-by-luizclas",
  "category": "Nikon Creators",
  "tags": null,
  "description": null,
  "author": "LUIZCLAS",
  "authorLink": null,
  "whiteBalance": null,
  "whiteBalanceShift": null,
  "activeDLighting": null,
  "evComp": null,
  "grain": null,
  "note": null,
  "np3": "PurpleM_LUIZCLAS.NP3",
  "images": [
    "PurpleM_LUIZCLAS.webp"
  ],
  "recipeLink": "https://imagingcloud.nikon.com/recipe/detail/?recipeId=01HXDGH5VZQPWC7MWB2513T2ZX"
}
